{
  "hash": "d62d01db",
  "configHash": "c8976631",
  "lockfileHash": "0bde91ab",
  "browserHash": "8c9954f4",
  "optimized": {
    "react/jsx-dev-runtime": {
      "src": "../../node_modules/react/jsx-dev-runtime.js",
      "file": "react_jsx-dev-runtime.js",
      "fileHash": "6cb48d71",
      "needsInterop": true
    },
    "react": {
      "src": "../../node_modules/react/index.js",
      "file": "react.js",
      "fileHash": "c7f17e1c",
      "needsInterop": true
    },
    "react-dom/client": {
      "src": "../../node_modules/react-dom/client.js",
      "file": "react-dom_client.js",
      "fileHash": "4abe1503",
      "needsInterop": true
    }
  },
  "chunks": {
    "chunk-XFZ2DVVZ": {
      "file": "chunk-XFZ2DVVZ.js"
    }
  }
}